ethapi/__init__.py
ethapi/api.py
ethapi/eth.py
python_ethapi-1.0.1.dev10.dist-info/DESCRIPTION.rst
python_ethapi-1.0.1.dev10.dist-info/METADATA
python_ethapi-1.0.1.dev10.dist-info/RECORD
python_ethapi-1.0.1.dev10.dist-info/WHEEL
python_ethapi-1.0.1.dev10.dist-info/metadata.json
python_ethapi-1.0.1.dev10.dist-info/pbr.json
python_ethapi-1.0.1.dev10.dist-info/top_level.txt
