Metadata-Version: 2.0
Name: python-ethapi
Version: 1.0.1.dev10
Summary: A library for api.ethermine.org
Home-page: https://git.cajun.pro/dirtycajunrice/python-ethapi
Author: Nicholas Totsch
Author-email: nicholas.totsch@gmail.com
License: UNKNOWN
Platform: UNKNOWN
Classifier: License :: OSI Approved :: Apache Software License
Classifier: Development Status :: 4 - Beta
Classifier: Intended Audience :: Developers
Classifier: Intended Audience :: System Administrators
Classifier: Intended Audience :: Information Technology
Classifier: Programming Language :: Python :: 3.5
Classifier: Topic :: Utilities
Requires-Dist: requests
